pyLoadingScreen/__init__.py
pyLoadingScreen/pyLoadingScreen.py
py_loading_screen-1.1.6.dist-info/LICENSE
py_loading_screen-1.1.6.dist-info/METADATA
py_loading_screen-1.1.6.dist-info/WHEEL
py_loading_screen-1.1.6.dist-info/top_level.txt
py_loading_screen-1.1.6.dist-info/RECORD
