Metadata-Version: 2.1
Name: py-loading-screen
Version: 1.1.6
Summary: Animated loading screen
Home-page: https://github.com/a-s-akulov/py-loading-screen/
Author: a.s.akulov
Author-email: a.c.akulov@mail.ru
License: UNKNOWN
Platform: UNKNOWN
Classifier: Programming Language :: Python :: 3
Classifier: License :: OSI Approved :: GNU General Public License v3 (GPLv3)
Classifier: Operating System :: OS Independent
Classifier: Development Status :: 5 - Production/Stable
Requires-Python: >=3.0
Requires-Dist: PyQt5 (>=5.0.0)
